mcts_co/__init__.py
mcts_co/optimizer.py
mcts_co/statistical_value.py
mcts_co-0.0.0.dist-info/LICENSE
mcts_co-0.0.0.dist-info/METADATA
mcts_co-0.0.0.dist-info/WHEEL
mcts_co-0.0.0.dist-info/top_level.txt
mcts_co-0.0.0.dist-info/RECORD
